MANIFEST.in
setup.py
ivs_cal.egg-info/PKG-INFO
ivs_cal.egg-info/SOURCES.txt
ivs_cal.egg-info/dependency_links.txt
ivs_cal.egg-info/not-zip-safe
ivs_cal.egg-info/requires.txt
ivs_cal.egg-info/top_level.txt
src/__init__.py
src/calculator.ui
src/conf.py
src/gui.py
src/gui_lin.py
src/ivs-cal
src/linearSystem.ui
src/mathlib.py
src/profiler.py
src/tester.py