Metadata-Version: 1.0
Name: ivs-cal
Version: 1.2
Summary: Calculator for IVS project.
Home-page: https://github.com/NoName115/IVS
Author: xbazik00, xkolcu00, xcubae00, xkurak00
Author-email: martin.bazik@gmail.com
License: GPL3
Platform: UNKNOWN
